odoo/addons/sale_dms_field/README.rst
odoo/addons/sale_dms_field/__init__.py
odoo/addons/sale_dms_field/__manifest__.py
odoo/addons/sale_dms_field/demo/sale_dms_data.xml
odoo/addons/sale_dms_field/i18n/it.po
odoo/addons/sale_dms_field/i18n/sale_dms_field.pot
odoo/addons/sale_dms_field/models/__init__.py
odoo/addons/sale_dms_field/models/sale_order.py
odoo/addons/sale_dms_field/readme/CONFIGURE.rst
odoo/addons/sale_dms_field/readme/CONTRIBUTORS.rst
odoo/addons/sale_dms_field/readme/CREDITS.rst
odoo/addons/sale_dms_field/readme/DESCRIPTION.rst
odoo/addons/sale_dms_field/static/description/icon.png
odoo/addons/sale_dms_field/static/description/index.html
odoo/addons/sale_dms_field/tests/__init__.py
odoo/addons/sale_dms_field/tests/test_sale_dms_field.py
odoo/addons/sale_dms_field/views/sale_order_view.xml
odoo_addon_sale_dms_field-16.0.1.0.0.4.dist-info/METADATA
odoo_addon_sale_dms_field-16.0.1.0.0.4.dist-info/WHEEL
odoo_addon_sale_dms_field-16.0.1.0.0.4.dist-info/top_level.txt
odoo_addon_sale_dms_field-16.0.1.0.0.4.dist-info/RECORD
